mipego/BayesOpt.py
mipego/Extension.py
mipego/InfillCriteria.py
mipego/SearchSpace.py
mipego/Solution.py
mipego/Surrogate.py
mipego/__init__.py
mipego/base.py
mipego/misc.py
mipego/utils.py
mipego/GaussianProcess/OWCK.py
mipego/GaussianProcess/OWCK_slave.py
mipego/GaussianProcess/__init__.py
mipego/GaussianProcess/boundary_handling.py
mipego/GaussianProcess/function.py
mipego/GaussianProcess/gpr.py
mipego/GaussianProcess/gprhao.py
mipego/GaussianProcess/kernel.py
mipego/GaussianProcess/setup.py
mipego/GaussianProcess/trend.py
mipego/GaussianProcess/utils.py
mipego/optimizer/OnePlusOne_CMA.py
mipego/optimizer/__init__.py
mipego/optimizer/mies.py
mipego/optimizer/utils.py
test/__init__.py
test/test_BO.py
test/test_SearchSpace.py
test/test_Solution.py
mipego-2.0.0.dist-info/LICENSE.txt
mipego-2.0.0.dist-info/METADATA
mipego-2.0.0.dist-info/WHEEL
mipego-2.0.0.dist-info/top_level.txt
mipego-2.0.0.dist-info/RECORD
