Metadata-Version: 2.1
Name: mipego
Version: 2.0.0
Summary: Mixed Integer Parallel - Efficient Global Optimization with GPU support
Home-page: https://github.com/wangronin/MIP-EGO
Author: Hao Wang and Bas van Stein
Author-email: wangronin@gmail.com
License: UNKNOWN
Keywords: bayesian optimization ego mixed-integer
Platform: UNKNOWN
Classifier: Development Status :: 5 - Production/Stable
Classifier: Intended Audience :: Science/Research
Classifier: Topic :: Scientific/Engineering :: Artificial Intelligence
Classifier: License :: OSI Approved :: MIT License
Classifier: Programming Language :: Python :: 2
Classifier: Programming Language :: Python :: 2.7
Classifier: Programming Language :: Python :: 3
Classifier: Programming Language :: Python :: 3.7
Classifier: Programming Language :: Python :: 3.8
Classifier: Programming Language :: Python :: 3.9
Requires-Dist: dill
Requires-Dist: joblib
Requires-Dist: numpy
Requires-Dist: pandas
Requires-Dist: pyDOE
Requires-Dist: scikit-learn
Requires-Dist: scipy
